Metadata-Version: 1.1
Name: pytest-easyread
Version: 0.1.0
Summary: pytest plugin that makes terminal printouts of the reports easier to read
Home-page: https://github.com/CrystalPea/pytest-easyread
Author: Pea Tyczynska
Author-email: m.a.tyczynska@gmail.com
License: BSD
Download-URL: https://github.com/CrystalPea/pytest-easyread/archive/0.1.tar.gz
Keywords: testing,readability,terminal
Platform: any
Classifier: Framework :: Pytest
Classifier: Programming Language :: Python :: 2
Classifier: Programming Language :: Python :: 3
